Workbook
Name CList: 'P&L Other Details'!$XFD$2:$XFD$251
Name SList: 'P&L Other Details'!$XFC$2:$XFC$42

Sheet Balance Sheet
A1: I | B1: EQUITY AND LIABILITIES
B2: 1 | C2: Shareholder’s fund
C3: A | D3: Share capital
D4: i | E4: Authorised | H4: Ai
D5: ii | E5: Issued, Subscribed and fully Paid up | H5: Aii
D6: iii | E6: Subscribed but not fully paid | H6: Aiii
D7: iv | E7: Total ( Aii +Aiii ) | J7: Aiv | K7: =SUM(I5:I6) -> 0
C8: B | D8: Reserves and Surplus
D9: i | E9: Capital Reserve | H9: Bi
D10: ii | E10: Capital Redemption Reserve | H10: bii
D11: iii | E11: Securities Premium Reserve | H11: biii
D12: iv | E12: Debentures Redemption Reserve | H12: biv
D13: v | E13: Revaluation Reserve | H13: bv
D14: vi | E14: Share options outstanding amount | H14: bvi
D15: vii | E15: Other reserve (specify nature and amount) | H15: bvii | I15: =SUM('Other reserve'!B2:B50) -> 0
D16: viii | E16: Surplus i.e. Balance in profit and loss account (Debit balance to be shown as –ve figure) | H16: bviii
D17: ix | E17: Total ( Bi + Bii + Biii + Biv + Bv + Bvi + Bvii + Bviii) | J17: bix | K17: =SUM(I9:I16) -> 0
C18: C | D18: Money received against share warrants | J18: 1C
C19: D | D19: Total Shareholder’s fund ( Aiv + Bix + 1C ) | J19: 1D | K19: =SUM(K7,K17,K18) -> 0
B20: 2 | C20: Share application money pending allotment
C21: i | D21: Pending for less than one year | H21: i
C22: ii | D22: Pending for more than one year | H22: ii
C23: iii | D23: Total ( i + ii ) | J23: 2 | K23: =SUM(I21:I22) -> 0
B24: 3 | C24: Non-current liabilities
C25: A | D25: Long-term borrowings
D26: i | E26: Bond / debentures
E27: a | F27: Foreign currency | H27: ia
E28: b | F28: Rupee | H28: ib
E29: c | F29: Total ( ia + ib ) | J29: ic | K29: =SUM(I27:I28) -> 0
D30: ii | E30: Term loans
E31: a | F31: Foreign currency | H31: iia
E32: b | F32: Rupee loans
F33: 1 | G33: From Banks | H33: b1
F34: 2 | G34: From others | H34: b2
F35: 3 | G35: Total ( b1 + b2 ) | H35: b3 | I35: =SUM(I33:I34) -> 0
E36: C | F36: Total Term loans ( iia + b3 ) | J36: iic | K36: =SUM(I31,I35) -> 0
D37: iii | E37: Deferred payment liabilities | J37: iii
D38: iv | E38: Deposits from related parties (see instructions) | J38: iv
D39: v | E39: Other deposits | J39: v
D40: vi | E40: Loans and advances from related parties (see instructions) | J40: vi
D41: vii | E41: Other loans and advances | J41: vii
D42: viii | E42: Long term maturities of finance lease obligations | J42: viii
D43: ix | E43: Total Long term borrowings ( ic + iic + iii + iv + v + vi + vii + viii) | J43: 3A | K43: =SUM(K29,K36:K42) -> 0
C44: B | D44: Deferred tax liabilities (net) | J44: 3B
C45: C | D45: Other long-term liabilities
D46: i | E46: Trade payables | H46: i
D47: ii | E47: Others | H47: ii
D48: iii | E48: Total Other long-term liabilities ( i + ii ) | J48: 3C | K48: =SUM(I46:I47) -> 0
C49: D | D49: Long-term provisions
D50: i | E50: Provision for employee benefits | H50: i
D51: ii | E51: Others | H51: ii
D52: iii | E52: Total ( i + ii ) | J52: 3D | K52: =SUM(I50:I51) -> 0
C53: E | D53: Total Non-current liabilities ( 3A + 3B + 3C + 3D ) | J53: 3E | K53: =SUM(K43:K44,K48,K52) -> 0
B54: 4 | C54: Current liabilities
C55: A | D55: Short-term borrowings
D56: i | E56: Loans repayable on demand
E57: a | F57: From Banks | H57: ia
E58: b | F58: From Non-Banking Finance Companies | H58: ib
E59: c | F59: From other financial institutions | H59: ic
E60: d | F60: From others | H60: id
E61: e | F61: Total Loans repayable on demand ( ia + ib + ic + id ) | J61: ie | K61: =SUM(I57:I60) -> 0
D62: ii | E62: Deposits from related parties (see instructions) | J62: ii
D63: iii | E63: Loans and advances from related parties (see instructions) | J63: iii
D64: iv | E64: Other loans and advances | J64: iv
D65: v | E65: Other deposits | J65: v
D66: vi | E66: Total Short-term borrowings ( ie + ii + iii + iv + v ) | J66: 4A | K66: =SUM(K61:K65) -> 0
C67: B | D67: Trade payables
E68: i | F68: Outstanding for more than 1 year | H68: i
E69: ii | F69: Others | H69: ii
E70: iii | F70: Total Trade payables ( i + ii ) | J70: 4B | K70: =SUM(I68:I69) -> 0
C71: C | D71: Other current liabilities
D72: i | E72: Current maturities of long-term debt | H72: i
D73: ii | E73: Current maturities of finance lease obligations | H73: ii
D74: iii | E74: Interest accrued but not due on borrowings | H74: iii
D75: iv | E75: Interest accrued and due on borrowings | H75: iv
D76: v | E76: Income received in advance | H76: v
D77: vi | E77: Unpaid dividends | H77: vi
D78: vii | E78: Application money received for allotment of securities and due for refund and interest accrued | H78: vii
D79: viii | E79: Unpaid matured deposits and interest accrued thereon | H79: viii
D80: ix | E80: Unpaid matured debentures and interest accrued thereon | H80: ix
D81: x | E81: Other payables | H81: x
D82: xi | E82: Total Other current liabilities ( i + ii + iii + iv + v + vi + vii + viii + ix + x ) | J82: 4C | K82: =SUM(I72:I81) -> 0
C83: D | D83: Short-term provisions
D84: i | E84: Provision for employee benefit | H84: i
D85: ii | E85: Provision for Income-tax | H85: ii
D86: iii | E86: Proposed Dividend | H86: iii
D87: iv | E87: Tax on dividend | H87: iv
D88: v | E88: Other | H88: v
D89: vi | E89: Total Short-term provisions ( i + ii + iii + iv + v ) | J89: 4D | K89: =SUM(I84:I88) -> 0
C90: E | D90: Total Current liabilities ( 4A + 4B + 4C + 4D ) | J90: 4E | K90: =SUM(K66,K70,K82,K89) -> 0
B91: Total Equity and liabilities ( 1D + 2 + 3E + 4E ) | J91: I | K91: =SUM(K19,K23,K53,K90) -> 0
A92: II | B92: ASSETS
B93: 1 | C93: Non-current assets
C94: A | D94: Fixed assets
D95: i | E95: Tangible assets
E96: a | F96: Gross block | H96: ia
E97: b | F97: Depreciation | H97: ib
E98: c | F98: Impairment losses | H98: ic
E99: d | F99: Net block ( ia – ib – ic ) | H99: id | I99: =I96-I97-I98 -> 0
D100: ii | E100: Intangible assets
...

Sheet Other reserve
A1: Particulars | B1: Amount

Sheet Manufacturing Account
A1: I | B1: Opening Inventory
B2: A | C2: i | D2: Opening stock of raw-material | H2: i
C3: ii | D3: Opening stock of Work in progress | H3: ii
C4: iii | D4: Total (i + ii) | J4: Aiii | K4: =SUM(I2:I3) -> 0
B5: B | C5: Purchases (net of refunds and duty or tax, if any) | J5: B
B6: C | C6: Direct wages | J6: C
B7: D | C7: Direct expenses ( Di + Dii + Diii ) | J7: D | K7: =SUM(I8:I10) -> 0
C8: i | D8: Carriage inward | H8: i
C9: ii | D9: Power and fuel | H9: ii
C10: iii | D10: Other direct expenses | H10: iii
B11: E | C11: Factory Overheads
C12: i | D12: Indirect wages | H12: i
C13: ii | D13: Factory rent and rates | H13: ii
C14: iii | D14: Factory Insurance | H14: iii
C15: iv | D15: Factory fuel and power | H15: iv
C16: v | D16: Factory general expenses | H16: v
C17: vi | D17: Depreciation of factory machinery | H17: vi
C18: Total ( i + ii + iii + iv + v + vi ) | J18: Evii | K18: =SUM(I12:I17) -> 0
B19: F | C19: Total of Debits to Manufacturing Account ( Aiii + B + C + D + Evii ) | J19: 1F | K19: =SUM(K4:K7,K18) -> 0
A20: 2 | B20: Closing Stock
B21: i | C21: Raw material | H21: 2i
B22: ii | C22: Work-in-progress | H22: 2ii
B23: Total ( 2i + 2ii ) | J23: 2 | K23: =SUM(I21:I22) -> 0
A24: 3 | B24: Cost of Goods Produced – transferred to Trading Account ( 1F – 2 ) | J24: 3 | K24: =K19-K23 -> 0

Sheet Trading Account
A1: CREDITS TO TRADING ACCOUNT
A2: 4 | B2: Revenue from operations
B3: A | C3: Sales/Gross receipts of business (net of returns and refunds and duty or tax, if any)
C4: i | D4: Sale of goods | H4: i
C5: ii | D5: Sale of services | H5: ii
C6: iii | D6: Other operating revenues (specify nature and amount) | H6: iii | I6: =SUM('Trading Other Details'!B3:B50) -> 0
C7: iv | D7: Total ( i + ii + iiic ) | J7: Aiv | K7: =SUM(I4:I6) -> 0
B8: B | C8: Gross receipts from Profession | J8: B
B9: C | C9: Duties, taxes and cess, received or receivable, in respect of goods and services sold or supplied
C10: i | D10: Union Excise duties | H10: i
C11: ii | D11: Service tax | H11: ii
C12: iii | D12: VAT/Sales tax | H12: iii
C13: iv | D13: Central Goods & Service Tax (CGST) | H13: iv
C14: v | D14: State Goods & Services Tax (SGST) | H14: v
C15: vi | D15: Integrated Goods & Services Tax (IGST) | H15: vi
C16: vii | D16: Union Territory Goods & Services Tax (UTGST) | H16: vii
C17: viii | D17: Any other duty, tax and cess | H17: viii
C18: ix | D18: Total ( i + ii + iii + iv + v + vi + vii + viii ) | J18: Cix | K18: =SUM(I10:I17) -> 0
B19: D | C19: Total Revenue from operations ( Aiv + B + Cix ) | J19: 4D | K19: =SUM(K7:K8,K18) -> 0
A20: 5 | B20: Closing Stock of Finished Stocks | J20: 5
A21: 6 | B21: Total of credits to Trading Account ( 4D + 5 ) | J21: 6 | K21: =SUM(K19:K20) -> 0
A22: DEBITS TO TRADING ACCOUNT
A23: 7 | B23: Opening Stock of Finished Goods 7 | J23: 7
A24: 8 | B24: Purchases (net of refunds and duty or tax, if any) | J24: 8
A25: 9 | B25: Direct Expenses (9i + 9ii + 9iii) | J25: 9 | K25: =SUM(I26:I28) -> 0
B26: i | C26: Carriage inward | H26: 9i
B27: ii | C27: Power and fuel | H27: 9ii
B28: iii | C28: Other direct expenses (specify nature and amount) | H28: 9iii | I28: =SUM('Trading Other Details'!E3:E50) -> 0
A29: 10 | B29: Duties and taxes, paid or payable, in respect of goods and services purchased
B30: i | C30: Custom duty | H30: 10i
B31: ii | C31: Counter vailing duty | H31: 10ii
B32: iii | C32: Special additional duty | H32: 10iii
B33: iv | C33: Union excise duty | H33: 10iv
B34: v | C34: Service tax | H34: 10v
B35: vi | C35: VAT/Sales tax | H35: 10vi
B36: vii | C36: Central Goods & Service Tax (CGST) | H36: 10vii
B37: viii | C37: State Goods & Services Tax (SGST) | H37: 10viii
B38: ix | C38: Integrated Goods & Services Tax (IGST) | H38: 10ix
B39: x | C39: Union Territory Goods & Services Tax (UTGST) | H39: 10x
B40: xi | C40: Any other tax, paid or payable | H40: 10xi
B41: xii | C41: Total ( 10i + 10ii + 10iii + 10iv + 10v + 10vi + 10vii + 10viii + 10ix + 10x + 10xi ) | J41: 10xii | K41: =SUM(I30:I40) -> 0
A42: 11 | B42: Cost of goods produced – Transferred from Manufacturing Account | J42: 11 | K42: ='Manufacturing Account'!K24 -> 0
A43: 12 | B43: Gross Profit from Business/Profession - transferred to Profit and Loss account ( 6 – 7 – 8 – 9 - 10xii -11 ) | J43: 12 | K43: =K21-K23-K24-K25-K41-K42 -> 0
A44: 12a | B44: Turnover from Intraday Trading | J44: 12a
A45: 12b | B45: Income from Intraday Trading | J45: 12b
A46: 12c | B46: Turnover from Futures & Options Trading | J46: 12a
A47: 12d | B47: Income from Futures & Options Trading - transferred to Profit and Loss account | J47: 12b

Sheet Trading Other Details
A1: Other operating revenues (specify nature and amount) | D1: Other direct expenses (specify nature and amount)
A2: Particulars | B2: Amount | D2: Particulars | E2: Amount

Sheet Profit and Loss Account
A1: CREDITS TO PROFIT AND LOSS ACCOUNT
A2: 13 | B2: Gross profit transferred from Trading Account | J2: 13 | K2: ='Trading Account'!K43+'Trading Account'!K45+'Trading Account'!K47 -> 0
A3: 14 | B3: Other income
B4: i | C4: Rent | H4: i
B5: ii | C5: Commission | H5: ii
B6: iii | C6: Dividend income | H6: iii
B7: iv | C7: Interest income | H7: iv
B8: v | C8: Profit on sale of fixed assets | H8: v
B9: vi | C9: Profit on sale of investment being securities chargeable to Securities Transaction Tax (STT) | H9: vi
B10: vii | C10: Profit on sale of other investment | H10: vii
B11: viii | C11: Gain (loss) on account of foreign exchange fluctuation u/s 43AA | H11: viii
B12: ix | C12: Profit on conversion of inventory into capital asset u/s 28(via) (Fair Market Value of inventory as on the date of conversion) | H12: ix
B13: x | C13: Agriculture income | H13: x
B14: xi | C14: Any other income (specify nature and amount) | H14: xi | I14: =SUM('P&L Other Details'!B3:B50) -> 0
B15: xii | C15: Total of other income ( i + ii + iii + iv + v + vi + vii + viii + ix + x + xic ) | J15: 14xii | K15: =SUM(I4:I14) -> 0
A16: 15 | B16: Total of credits to profit and loss account (13+14xii) | J16: 15 | K16: =SUM(K2,K15) -> 0
A17: DEBITS TO PROFIT AND LOSS ACCOUNT
A18: 16 | B18: Freight outward | J18: 16
A19: 17 | B19: Consumption of stores and spare parts | J19: 17
A20: 18 | B20: Power and fuel | J20: 18
A21: 19 | B21: Rents | J21: 19
A22: 20 | B22: Repairs to building | J22: 20
A23: 21 | B23: Repairs to machinery | J23: 21
A24: 22 | B24: Compensation to employees
B25: i | C25: Salaries and wages | H25: 22i
B26: ii | C26: Bonus | H26: 22ii
B27: iii | C27: Reimbursement of medical expenses | H27: 22iii
B28: iv | C28: Leave encashment | H28: 22iv
B29: v | C29: Leave travel benefits | H29: 22v
B30: vi | C30: Contribution to approved superannuation fund | H30: 22vi
B31: vii | C31: Contribution to recognised provident fund | H31: 22vii
B32: viii | C32: Contribution to recognised gratuity fund | H32: 22viii
B33: ix | C33: Contribution to any other fund | H33: 22ix
B34: x | C34: Any other benefit to employees in respect of which an expenditure has been incurred | H34: 22x
B35: xi | C35: Total compensation to employees (total of 22i to 22x) | J35: 22xi | K35: =SUM(I25:I34) -> 0
B36: xii | C36: Any compensation amount , included in 22xi, paid to non-residents | H36: xii
A37: 23 | B37: Insurance
B38: i | C38: Medical Insurance | H38: 23i
B39: ii | C39: Life Insurance | H39: 23ii
B40: iii | C40: Keyman's Insurance | H40: 23iii
B41: iv | C41: Other Insurance including factory, office, car, goods etc. | H41: 23iv
B42: v | C42: Total expenditure on insurance ( 23i + 23ii + 23iii + 23iv ) | J42: 23v | K42: =SUM(I38:I41) -> 0
A43: 24 | B43: Workmen and staff welfare expenses | J43: 24
A44: 25 | B44: Entertainment | J44: 25
A45: 26 | B45: Hospitality | J45: 26
A46: 27 | B46: Conference | J46: 27
A47: 28 | B47: Sales promotion including publicity (other than advertisement) | J47: 28
A48: 29 | B48: Advertisement | J48: 29
A49: 30 | B49: Commission
B50: i | C50: Paid outside India, or paid in India to a non-resident other than a company or a foreign company | H50: i
B51: ii | C51: To others | H51: ii
B52: iii | C52: Total ( i + ii ) | J52: 30iii | K52: =SUM(I48:I51) -> 0
A53: 31 | B53: Royalty
B54: i | C54: Paid outside India, or paid in India to a non-resident other than a company or a foreign company | H54: i
B55: ii | C55: To others | H55: ii
B56: iii | C56: Total ( i + ii ) | J56: 31iii | K56: =SUM(I52:I55) -> 0
A57: 32 | B57: Professional / Consultancy fees / Fee for technical services
B58: i | C58: Paid outside India, or paid in India to a non-resident other than a company or a foreign company | H58: i
B59: ii | C59: To others | H59: ii
B60: iii | C60: Total ( i + ii ) | J60: 32iii | K60: =SUM(I56:I59) -> 0
A61: 33 | B61: Hotel, boarding and Lodging | J61: 33
A62: 34 | B62: Traveling expenses other than on foreign traveling | J62: 34
A63: 35 | B63: Foreign traveling expenses | J63: 35
A64: 36 | B64: Conveyance expenses | J64: 36
A65: 37 | B65: Telephone expenses | J65: 37
A66: 38 | B66: Guest House expenses | J66: 38
A67: 39 | B67: Club expenses | J67: 39
A68: 40 | B68: Festival celebration expenses | J68: 40
A69: 41 | B69: Scholarship | J69: 41
A70: 42 | B70: Gift | J70: 42
A71: 43 | B71: Donation | J71: 43
A72: 44 | B72: Rates and taxes, paid or payable to Government or any local body (excluding taxes on income)
B73: i | C73: Union excise duty | H73: 44i
B74: ii | C74: Service tax | H74: 44ii
B75: iii | C75: VAT/Sales tax | H75: 44iii
B76: iv | C76: Cess | H76: 44iv
B77: v | C77: Central Goods & Service Tax (CGST) | H77: 44v
B78: vi | C78: State Goods & Services Tax (SGST) | H78: 44vi
B79: vii | C79: Integrated Goods & Services Tax (IGST) | H79: 44vii
B80: viii | C80: Union Territory Goods & Services Tax (UTGST) | H80: 44viii
B81: ix | C81: Any other rate, tax, duty or cess incl STT and CTT | H81: 44ix
B82: x | C82: Total rates and taxes paid or payable ( 44i + 44ii + 44iii + 44iv + 44v + 44vi + 44vii + 44viii + 44ix ) | J82: 44x | K82: =SUM(I73:I81) -> 0
A83: 45 | B83: Audit fee | J83: 45
A84: 46 | B84: Other expenses (Specify amount and nature) | J84: 46 | K84: =SUM('P&L Other Details'!E3:E50) -> 0
A85: 47 | B85: Bad debts
B86: i | C86: Bad Debt for amount of Rs. 1 lakh or more, where PAN is available | H86: 47i | I86: =SUM('P&L Other Details'!I3:I50) -> 0
B87: ii | C87: Bad Debt for amount of Rs. 1 lakh or more, where PAN is not available (provide name and complete address) | H87: 47ii | I87: =SUM('P&L Other Details'!T3:T50) -> 0
B88: iii | C88: Others (amounts less than Rs. 1 lakh) | H88: 47iii | I88: =SUM('P&L Other Details'!W3:W50) -> 0
B89: iv | C89: Total Bad Debt (47i + 47ii + 47iii ) | J89: 47iv | K89: =SUM(I86:I88) -> 0
A90: 48 | B90: Provision for bad and doubtful debts | J90: 48
A91: 49 | B91: Other provisions | J91: 49
A92: 50 | B92: Profit before interest, depreciation and taxes [15 – (16 to 21 + 22xi + 23v + 24 to 29 + 30iii + 31iii + 32iii + 33 to 43 + 44x + 45 + 46iii + 47iv + 48 + 49)] | J92: 50 | K92: =K16-SUM(K18:K23,K35,K42:K48,K52,K56,K60:K71,K82:K84,K89:K91) -> 0
A93: 51 | B93: Interest
B94: i | C94: Paid outside India, or paid in India to a non-resident other than a company or a foreign company | H94: i
B95: ii | C95: To others | H95: ii
B96: iii | C96: Total ( i + ii ) | J96: 51iii | K96: =SUM(I92:I95) -> 0
A97: 52 | B97: Depreciation and amoritisation | J97: 52
A98: 53 | B98: Profit before taxes (50-51iii-52) | J98: 53 | K98: =K92-K96-K97 -> 0
A99: PROVISIONS FOR TAX AND APPROPRIATIONS
A100: 54 | B100: Provision for current tax | J100: 54
...

Sheet P&L Other Details
A1: Any other income (specify nature and amount) | D1: Other expenses (Specify amount and nature) | G1: Bad Debt for amount of Rs. 1 lakh or more, where PAN is available | K1: Bad Debt for amount of Rs. 1 lakh or more, where PAN is not available (provide name and complete address) | V1: Others (amounts less than Rs. 1 lakh) | XFC1: STATE | XFD1: COUNTRY
A2: Particulars | B2: Amount | D2: Particulars | E2: Amount | G2: PAN of person | H2: AADHAAR of person | I2: Amount | K2: Name of person | L2: Flat/ Door /Block No. | M2: Name of premises/ building/ village | N2: Road/ Street/ Post office | O2: Area/ Locality | P2: Town/ City/ District | Q2: State | R2: Country | S2: PIN/ZIP Code | T2: Amount | V2: Particulars | W2: Amount | XFC2: ANDAMAN AND NICOBAR ISLANDS | XFD2: AFGHANISTAN
A3: Liabilities written back | XFC3: ANDHRA PRADESH | XFD3: ALAND ISLANDS
XFC4: ARUNACHAL PRADESH | XFD4: ALBANIA
XFC5: ASSAM | XFD5: ALGERIA
XFC6: BIHAR | XFD6: AMERICAN SAMOA
XFC7: CHANDIGARH | XFD7: ANDORRA
XFC8: DADRA & NAGAR HAVELI | XFD8: ANGOLA
XFC9: DAMAN & DIU | XFD9: ANGUILLA
XFC10: DELHI | XFD10: ANTARCTICA
XFC11: GOA | XFD11: ANTIGUA AND BARBUDA
XFC12: GUJARAT | XFD12: ARGENTINA
XFC13: HARYANA | XFD13: ARMENIA
XFC14: HIMACHAL PRADESH | XFD14: ARUBA
XFC15: JAMMU & KASHMIR | XFD15: AUSTRALIA
... XFC42: STATE OUTSIDE INDIA | XFD42: CANADA
XFD43: CAYMAN ISLANDS
XFD44: CENTRAL AFRICAN REPUBLIC
XFD45: CHAD
XFD46: CHILE
XFD47: CHINA
XFD48: CHRISTMAS ISLAND
XFD49: COCOS (KEELING) ISLANDS
XFD50: COLOMBIA
XFD51: COMOROS
XFD52: CONGO
XFD53: CONGO (DEMOCRATIC REPUBLIC OF THE)
XFD54: COOK ISLANDS
... XFD251: OTHERS
