Workbook
Name CList: 'P&L Other Details'!$XFD$2:$XFD$251
Name SList: 'P&L Other Details'!$XFC$2:$XFC$42

Sheet Balance Sheet
A1: A | B1: SOURCES OF FUNDS
B2: 1 | C2: Partners' / Members' fund
C3: a | D3: Partners' / members' capital | J3: a
C4: b | D4: Reserves and Surplus
D5: i | E5: Revaluation Reserve | H5: Bi
D6: ii | E6: Capital Reserve | H6: bii
D7: iii | E7: Statutory Reserve | H7: biii
D8: iv | E8: Any other Reserve | H8: biv
D9: v | E9: Credit balance of Profit and loss account | H9: bv
D10: vi | E10: Total (bi+bii+biii+biv+bv) | J10: bvi | K10: =SUM(I5:I9) -> 0
C11: c | D11: Total partners' / members' fund (a+bvi) | J11: 1c | K11: =SUM(K3,K10) -> 0
B12: 2 | C12: Loan funds
C13: a | D13: Secured loans
D14: i | E14: Foreign Currency Loans | H14: ai
D15: ii | E15: Rupee Loans
E16: A | F16: From Banks | H16: iiA
E17: B | F17: From others | H17: iiB
E18: C | F18: Total (iiA+iiB) | H18: iiC | I18: =SUM(I16:I17) -> 0
D19: iii | E19: Total secured loans (ai+aiiC) | J19: aiii | K19: =SUM(I14,I18) -> 0
C20: b | D20: Unsecured loans (including deposits)
D21: i | E21: Foreign Currency Loans | H21: bi
D22: ii | E22: Rupee Loans
E23: A | F23: From Banks | H23: iiA
E24: B | F24: From persons specified in section 40A(2)(b) of the I.T. Act | H24: iiB
E25: C | F25: From others | H25: iiC
E26: D | F26: Total Rupee Loans (iiA+iiB+iiC) | H26: iiD | I26: =SUM(I23:I25) -> 0
D27: iii | E27: Total unsecured loans (bi+biiD) | J27: biii | K27: =SUM(I21,I26) -> 0
C28: C | D28: Total Loan Funds (aiii+biii) | J28: 2c | K28: =SUM(K19,K27) -> 0
B29: 3 | C29: Deferred tax liability | J29: 3
B30: 4 | C30: Advances
C31: i | D31: From persons specified in section 40A(2)(b) of I.T. Act | H31: i
C32: ii | D32: From others | H32: ii
C33: iii | D33: Total Advances (i + ii) | J33: 4iii | K33: =SUM(I31:I32) -> 0
B34: 5 | C34: Sources of funds (1c+2c+3+4iii) | J34: 5 | K34: =SUM(K11,K28,K29,K33) -> 0
A35: B | B35: APPLICATION OF FUNDS
B36: 1 | C36: Fixed assets
C37: a | D37: Gross: Block | H37: 1a
C38: b | D38: Depreciation | H38: 1b
C39: c | D39: Net Block (a-b) | H39: 1c | I39: =I37-I38 -> 0
C40: d | D40: Capital work-in-progress | H40: 1d
C41: e | D41: Total (1c+1d) | J41: 1e | K41: =SUM(I39:I40) -> 0
B42: 2 | C42: Investments
C43: a | D43: Long-term investments
D44: i | E44: Investment in property | H44: i
D45: ii | E45: Equity instruments
E46: A | F46: Listed equities | H46: iiA
E47: B | F47: Unlisted equities | H47: iiB
E48: C | F48: Total | H48: iiC | I48: =SUM(I46:I47) -> 0
D49: iii | E49: Preference shares | H49: iii
D50: iv | E50: Government or trust securities | H50: iv
D51: v | E51: Debenture or bonds | H51: v
D52: vi | E52: Mutual funds | H52: vi
D53: vii | E53: Others | H53: vii
D54: viii | E54: Total Long-term investments (i+iiC+iii+iv+v+vi+vii) | J54: aviii | K54: =SUM(I44,I48:I53) -> 0
C55: b | D55: Short-term investments
D56: i | E56: Equity instruments
E57: A | F57: Listed equities | H57: iA
E58: B | F58: Unlisted equities | H58: iB
E59: C | F59: Total | H59: iC | I59: =SUM(I57:I58) -> 0
D60: ii | E60: Preference shares | H60: ii
D61: iii | E61: Government or trust securities | H61: iii
D62: iv | E62: Debenture or bonds | H62: iv
D63: v | E63: Mutual funds | H63: v
D64: vi | E64: Others | H64: vi
D65: vii | E65: Total Short-term investments (iC+ii+iii+iv+v+vi) | J65: bvii | K65: =SUM(I59:I64) -> 0
C66: c | D66: Total investments (aviii+bvii) | J66: 2c | K66: =SUM(K54,K65) -> 0
B67: 3 | C67: Current assets, loans and advances
C68: a | D68: Current assets
D69: i | E69: Inventories
E70: A | F70: Raw materials | H70: iA
E71: B | F71: Work-in-progress | H71: iB
E72: C | F72: Finished goods | H72: iC
E73: D | F73: Stock-in-trade (in respect of goods acquired for trading) | H73: iD
E74: E | F74: Stores/consumables including packing material | H74: iE
E75: F | F75: Loose tools | H75: iF
E76: G | F76: Others | H76: iG
E77: H | F77: Total (iA+iB+iC+iD+iE+iF+iG) | J77: iH | K77: =SUM(I70:I76) -> 0
D78: ii | E78: Sundry Debtors
E79: A | F79: Outstanding for more than one year | H79: iiA
E80: B | F80: Others | H80: iiB
E81: C | F81: Total Sundry Debtors (iiA+iiB) | J81: iiC | K81: =SUM(I79:I80) -> 0
D82: iii | E82: Cash and Bank Balances
E83: A | F83: Balance with banks | H83: iiiA
E84: B | F84: Cash in hand | H84: iiiB
E85: C | F85: Others | H85: iiiC
E86: D | F86: Total Cash and cash equivalents (iiiA+iiiB+iiiC) | J86: iiiD | K86: =SUM(I83:I85) -> 0
D87: iv | E87: Other Current Assets | J87: aiv
D88: v | E88: Total current assets (iH+iiC+iiiD+aiv) | J88: av | K88: =SUM(K77,K81,K86:K87) -> 0
C89: b | D89: Loans and advances
D90: i | E90: Advances recoverable in cash or in kind or for value to be received | H90: bi
D91: ii | E91: Deposits, loans and advances to corporate and others | H91: bii
D92: iii | E92: Balance with Revenue Authorities | H92: biii
D93: iv | E93: Total (bi+bii+biii) | J93: biv | K93: =SUM(I90:I92) -> 0
D94: v | E94: Loans and advances included in biv which is
E95: a | F95: for the purpose of business or profession | H95: va
E96: b | F96: not for the purpose of business or profession | H96: vb
C97: c | D97: Total (av+biv) | J97: 3c | K97: =SUM(K88,K93) -> 0
C98: d | D98: Current liabilities and provisions
D99: i | E99: Current liabilities
E100: A | F100: Sundry Creditors
...

Sheet Manufacturing Account
A1: I | B1: Opening Inventory
B2: A | C2: i | D2: Opening stock of raw-material | H2: i
C3: ii | D3: Opening stock of Work in progress | H3: ii
C4: iii | D4: Total (i + ii) | J4: Aiii | K4: =SUM(I2:I3) -> 0
B5: B | C5: Purchases (net of refunds and duty or tax, if any) | J5: B
B6: C | C6: Direct wages | J6: C
B7: D | C7: Direct expenses ( Di + Dii + Diii ) | J7: D | K7: =SUM(I8:I10) -> 0
C8: i | D8: Carriage inward | H8: i
C9: ii | D9: Power and fuel | H9: ii
C10: iii | D10: Other direct expenses | H10: iii
B11: E | C11: Factory Overheads
C12: i | D12: Indirect wages | H12: i
C13: ii | D13: Factory rent and rates | H13: ii
C14: iii | D14: Factory Insurance | H14: iii
C15: iv | D15: Factory fuel and power | H15: iv
C16: v | D16: Factory general expenses | H16: v
C17: vi | D17: Depreciation of factory machinery | H17: vi
C18: Total ( i + ii + iii + iv + v + vi ) | J18: Evii | K18: =SUM(I12:I17) -> 0
B19: F | C19: Total of Debits to Manufacturing Account ( Aiii + B + C + D + Evii ) | J19: 1F | K19: =SUM(K4:K7,K18) -> 0
A20: 2 | B20: Closing Stock
B21: i | C21: Raw material | H21: 2i
B22: ii | C22: Work-in-progress | H22: 2ii
B23: Total ( 2i + 2ii ) | J23: 2 | K23: =SUM(I21:I22) -> 0
A24: 3 | B24: Cost of Goods Produced – transferred to Trading Account ( 1F – 2 ) | J24: 3 | K24: =K19-K23 -> 0

Sheet Trading Account
A1: CREDITS TO TRADING ACCOUNT
A2: 4 | B2: Revenue from operations
B3: A | C3: Sales/Gross receipts of business (net of returns and refunds and duty or tax, if any)
C4: i | D4: Sale of goods | H4: i
C5: ii | D5: Sale of services | H5: ii
C6: iii | D6: Other operating revenues (specify nature and amount) | H6: iii | I6: =SUM('Trading Other Details'!B3:B50) -> 0
C7: iv | D7: Total ( i + ii + iiic ) | J7: Aiv | K7: =SUM(I4:I6) -> 0
B8: B | C8: Gross receipts from Profession | J8: B
B9: C | C9: Duties, taxes and cess, received or receivable, in respect of goods and services sold or supplied
C10: i | D10: Union Excise duties | H10: i
C11: ii | D11: Service tax | H11: ii
C12: iii | D12: VAT/Sales tax | H12: iii
C13: iv | D13: Central Goods & Service Tax (CGST) | H13: iv
C14: v | D14: State Goods & Services Tax (SGST) | H14: v
C15: vi | D15: Integrated Goods & Services Tax (IGST) | H15: vi
C16: vii | D16: Union Territory Goods & Services Tax (UTGST) | H16: vii
C17: viii | D17: Any other duty, tax and cess | H17: viii
C18: ix | D18: Total ( i + ii + iii + iv + v + vi + vii + viii ) | J18: Cix | K18: =SUM(I10:I17) -> 0
B19: D | C19: Total Revenue from operations ( Aiv + B + Cix ) | J19: 4D | K19: =SUM(K7:K8,K18) -> 0
A20: 5 | B20: Closing Stock of Finished Stocks | J20: 5
A21: 6 | B21: Total of credits to Trading Account ( 4D + 5 ) | J21: 6 | K21: =SUM(K19:K20) -> 0
A22: DEBITS TO TRADING ACCOUNT
A23: 7 | B23: Opening Stock of Finished Goods | J23: 7
A24: 8 | B24: Purchases (net of refunds and duty or tax, if any) | J24: 8
A25: 9 | B25: Direct Expenses (9i + 9ii + 9iii) | J25: 9 | K25: =SUM(I26:I28) -> 0
B26: i | C26: Carriage inward | H26: 9i
B27: ii | C27: Power and fuel | H27: 9ii
B28: iii | C28: Other direct expenses (specify nature and amount) | H28: 9iii | I28: =SUM('Trading Other Details'!E3:E50) -> 0
A29: 10 | B29: Duties and taxes, paid or payable, in respect of goods and services purchased
B30: i | C30: Custom duty | H30: 10i
B31: ii | C31: Counter vailing duty | H31: 10ii
B32: iii | C32: Special additional duty | H32: 10iii
B33: iv | C33: Union excise duty | H33: 10iv
B34: v | C34: Service tax | H34: 10v
B35: vi | C35: VAT/Sales tax | H35: 10vi
B36: vii | C36: Central Goods & Service Tax (CGST) | H36: 10vii
B37: viii | C37: State Goods & Services Tax (SGST) | H37: 10viii
B38: ix | C38: Integrated Goods & Services Tax (IGST) | H38: 10ix
B39: x | C39: Union Territory Goods & Services Tax (UTGST) | H39: 10x
B40: xi | C40: Any other tax, paid or payable | H40: 10xi
B41: xii | C41: Total ( 10i + 10ii + 10iii + 10iv + 10v + 10vi + 10vii + 10viii + 10ix + 10x + 10xi ) | J41: 10xii | K41: =SUM(I30:I40) -> 0
A42: 11 | B42: Cost of goods produced – Transferred from Manufacturing Account | J42: 11 | K42: ='Manufacturing Account'!K24 -> 0
A43: 12 | B43: Gross Profit from Business/Profession - transferred to Profit and Loss account ( 6 – 7 – 8 – 9 - 10xii -11 ) | J43: 12 | K43: =K21-K23-K24-K25-K41-K42 -> 0
A44: 12a | B44: Turnover from Intraday Trading | J44: 12a
A45: 12b | B45: Income from Intraday Trading | J45: 12b
A46: 12c | B46: Turnover from Futures & Options Trading | J46: 12a
A47: 12d | B47: Income from Futures & Options Trading - transferred to Profit and Loss account | J47: 12b

Sheet Trading Other Details
A1: Other operating revenues (specify nature and amount) | D1: Other direct expenses (specify nature and amount)
A2: Particulars | B2: Amount | D2: Particulars | E2: Amount

Sheet Profit and Loss Account
A1: CREDITS TO PROFIT AND LOSS ACCOUNT
A2: 13 | B2: Gross profit transferred from Trading Account | J2: 13 | K2: ='Trading Account'!K43+'Trading Account'!K45+'Trading Account'!K47 -> 0
A3: 14 | B3: Other income
B4: i | C4: Rent | H4: i
B5: ii | C5: Commission | H5: ii
B6: iii | C6: Dividend income | H6: iii
B7: iv | C7: Interest income | H7: iv
B8: v | C8: Profit on sale of fixed assets | H8: v
B9: vi | C9: Profit on sale of investment being securities chargeable to Securities Transaction Tax (STT) | H9: vi
B10: vii | C10: Profit on sale of other investment | H10: vii
B11: viii | C11: Gain (loss) on account of foreign exchange fluctuation u/s 43AA | H11: viii
B12: ix | C12: Profit on conversion of inventory into capital asset u/s 28(via) (Fair Market Value of inventory as on the date of conversion) | H12: ix
B13: x | C13: Agriculture income | H13: x
B14: xi | C14: Any other income (specify nature and amount) | H14: xi | I14: =SUM('P&L Other Details'!B3:B50) -> 0
B15: xii | C15: Total of other income ( i + ii + iii + iv + v + vi + vii + viii + ix + x + xic ) | J15: 14xii | K15: =SUM(I4:I14) -> 0
A16: 15 | B16: Total of credits to profit and loss account (13+14xii) | J16: 15 | K16: =SUM(K2,K15) -> 0
A17: DEBITS TO PROFIT AND LOSS ACCOUNT
A18: 16 | B18: Freight outward | J18: 16
A19: 17 | B19: Consumption of stores and spare parts | J19: 17
A20: 18 | B20: Power and fuel | J20: 18
A21: 19 | B21: Rents | J21: 19
A22: 20 | B22: Repairs to building | J22: 20
A23: 21 | B23: Repairs to machinery | J23: 21
A24: 22 | B24: Compensation to employees
B25: i | C25: Salaries and wages | H25: 22i
B26: ii | C26: Bonus | H26: 22ii
B27: iii | C27: Reimbursement of medical expenses | H27: 22iii
B28: iv | C28: Leave encashment | H28: 22iv
B29: v | C29: Leave travel benefits | H29: 22v
B30: vi | C30: Contribution to approved superannuation fund | H30: 22vi
B31: vii | C31: Contribution to recognised provident fund | H31: 22vii
B32: viii | C32: Contribution to recognised gratuity fund | H32: 22viii
B33: ix | C33: Contribution to any other fund | H33: 22ix
B34: x | C34: Any other benefit to employees in respect of which an expenditure has been incurred | H34: 22x
B35: xi | C35: Total compensation to employees (total of 22i to 22x) | J35: 22xi | K35: =SUM(I25:I34) -> 0
B36: xii | C36: Any compensation amount , included in 22xi, paid to non-residents | H36: xii
A37: 23 | B37: Insurance
B38: i | C38: Medical Insurance | H38: 23i
B39: ii | C39: Life Insurance | H39: 23ii
B40: iii | C40: Keyman's Insurance | H40: 23iii
B41: iv | C41: Other Insurance including factory, office, car, goods etc. | H41: 23iv
B42: v | C42: Total expenditure on insurance ( 23i + 23ii + 23iii + 23iv ) | J42: 23v | K42: =SUM(I38:I41) -> 0
A43: 24 | B43: Workmen and staff welfare expenses | J43: 24
A44: 25 | B44: Entertainment | J44: 25
A45: 26 | B45: Hospitality | J45: 26
A46: 27 | B46: Conference | J46: 27
A47: 28 | B47: Sales promotion including publicity (other than advertisement) | J47: 28
A48: 29 | B48: Advertisement | J48: 29
A49: 30 | B49: Commission
B50: i | C50: Paid outside India, or paid in India to a non-resident other than a company or a foreign company | H50: i
B51: ii | C51: To others | H51: ii
B52: iii | C52: Total ( i + ii ) | J52: 30iii | K52: =SUM(I48:I51) -> 0
A53: 31 | B53: Royalty
B54: i | C54: Paid outside India, or paid in India to a non-resident other than a company or a foreign company | H54: i
B55: ii | C55: To others | H55: ii
B56: iii | C56: Total ( i + ii ) | J56: 31iii | K56: =SUM(I52:I55) -> 0
A57: 32 | B57: Professional / Consultancy fees / Fee for technical services
B58: i | C58: Paid outside India, or paid in India to a non-resident other than a company or a foreign company | H58: i
B59: ii | C59: To others | H59: ii
B60: iii | C60: Total ( i + ii ) | J60: 32iii | K60: =SUM(I56:I59) -> 0
A61: 33 | B61: Hotel, boarding and Lodging | J61: 33
A62: 34 | B62: Traveling expenses other than on foreign traveling | J62: 34
A63: 35 | B63: Foreign traveling expenses | J63: 35
A64: 36 | B64: Conveyance expenses | J64: 36
A65: 37 | B65: Telephone expenses | J65: 37
A66: 38 | B66: Guest House expenses | J66: 38
A67: 39 | B67: Club expenses | J67: 39
A68: 40 | B68: Festival celebration expenses | J68: 40
A69: 41 | B69: Scholarship | J69: 41
A70: 42 | B70: Gift | J70: 42
A71: 43 | B71: Donation | J71: 43
A72: 44 | B72: Rates and taxes, paid or payable to Government or any local body (excluding taxes on income)
B73: i | C73: Union excise duty | H73: 44i
B74: ii | C74: Service tax | H74: 44ii
B75: iii | C75: VAT/Sales tax | H75: 44iii
B76: iv | C76: Cess | H76: 44iv
B77: v | C77: Central Goods & Service Tax (CGST) | H77: 44v
B78: vi | C78: State Goods & Services Tax (SGST) | H78: 44vi
B79: vii | C79: Integrated Goods & Services Tax (IGST) | H79: 44vii
B80: viii | C80: Union Territory Goods & Services Tax (UTGST) | H80: 44viii
B81: ix | C81: Any other rate, tax, duty or cess incl STT and CTT | H81: 44ix
B82: x | C82: Total rates and taxes paid or payable ( 44i + 44ii + 44iii + 44iv + 44v + 44vi + 44vii + 44viii + 44ix ) | J82: 44x | K82: =SUM(I73:I81) -> 0
A83: 45 | B83: Audit fee | J83: 45
A84: 46 | B84: Salary/Remuneration to Partners of the firm | J84: 46
A85: 47 | B85: Other expenses (Specify amount and nature) | J85: 47 | K85: =SUM('P&L Other Details'!E3:E50) -> 0
A86: 48 | B86: Bad debts
B87: i | C87: Bad Debt for amount of Rs. 1 lakh or more, where PAN is available | H87: 48i | I87: =SUM('P&L Other Details'!I3:I50) -> 0
B88: ii | C88: Bad Debt for amount of Rs. 1 lakh or more, where PAN is not available (provide name and complete address) | H88: 48ii | I88: =SUM('P&L Other Details'!T3:T50) -> 0
B89: iii | C89: Others (amounts less than Rs. 1 lakh) | H89: 48iii | I89: =SUM('P&L Other Details'!W3:W50) -> 0
B90: iv | C90: Total Bad Debt (47i + 47ii + 47iii ) | J90: 48iv | K90: =SUM(I87:I89) -> 0
A91: 49 | B91: Provision for bad and doubtful debts | J91: 49
A92: 40 | B92: Other provisions | J92: 50
A93: 51 | B93: Profit before interest, depreciation and taxes [15 – (16 to 21 + 22xi+23v+24 to 29 +30iii+31iii+32iii+33 to 43 +44x+45+46+47+48iv+49+50) ] | J93: 51 | K93: =K16-SUM(K18:K23,K35,K42:K48,K52,K56,K60:K71,K82:K85,K90:K92) -> 0
A94: 52 | B94: Interest
B95: i | C95: Paid outside India, or paid in India to a non-resident other than a company or a foreign company
C96: a | D96: To Partners | H96: a
C97: b | D97: To Others | H97: b
B98: ii | C98: Paid in India, or paid to a resident
C99: a | D99: To Partners | H99: a
C100: b | D100: To Others | H100: b
...

Sheet P&L Other Details
A1: Any other income (specify nature and amount) | D1: Other expenses (Specify amount and nature) | G1: Bad Debt for amount of Rs. 1 lakh or more, where PAN is available | K1: Bad Debt for amount of Rs. 1 lakh or more, where PAN is not available (provide name and complete address) | V1: Others (amounts less than Rs. 1 lakh) | XFC1: STATE | XFD1: COUNTRY
A2: Particulars | B2: Amount | D2: Particulars | E2: Amount | G2: PAN of person | H2: AADHAAR of person | I2: Amount | K2: Name of person | L2: Flat/ Door /Block No. | M2: Name of premises/ building/ village | N2: Road/ Street/ Post office | O2: Area/ Locality | P2: Town/ City/ District | Q2: State | R2: Country | S2: PIN/ZIP Code | T2: Amount | V2: Particulars | W2: Amount | XFC2: ANDAMAN AND NICOBAR ISLANDS | XFD2: AFGHANISTAN
A3: Liabilities written back | XFC3: ANDHRA PRADESH | XFD3: ALAND ISLANDS
XFC4: ARUNACHAL PRADESH | XFD4: ALBANIA
XFC5: ASSAM | XFD5: ALGERIA
XFC6: BIHAR | XFD6: AMERICAN SAMOA
XFC7: CHANDIGARH | XFD7: ANDORRA
XFC8: DADRA & NAGAR HAVELI | XFD8: ANGOLA
XFC9: DAMAN & DIU | XFD9: ANGUILLA
XFC10: DELHI | XFD10: ANTARCTICA
XFC11: GOA | XFD11: ANTIGUA AND BARBUDA
XFC12: GUJARAT | XFD12: ARGENTINA
XFC13: HARYANA | XFD13: ARMENIA
XFC14: HIMACHAL PRADESH | XFD14: ARUBA
XFC15: JAMMU & KASHMIR | XFD15: AUSTRALIA
... XFC42: STATE OUTSIDE INDIA | XFD42: CANADA
XFD43: CAYMAN ISLANDS
XFD44: CENTRAL AFRICAN REPUBLIC
XFD45: CHAD
XFD46: CHILE
XFD47: CHINA
XFD48: CHRISTMAS ISLAND
XFD49: COCOS (KEELING) ISLANDS
XFD50: COLOMBIA
XFD51: COMOROS
XFD52: CONGO
XFD53: CONGO (DEMOCRATIC REPUBLIC OF THE)
XFD54: COOK ISLANDS
... XFD251: OTHERS
